<?xml version="1.0" encoding="utf-8"?>
<root xmlns:android="http://schemas.android.com/apk/res/android">
    <!-- init section is always evaluated once per architecture -->
    <init>
        <log text="TapBootstrap Android Build init"/>
    </init>

    <!-- optional additions to proguard -->
    <proguardAdditions>
        <insert>
        </insert>
    </proguardAdditions>

    <!-- optional files or directories to copy to Intermediate/Android/APK -->
    <resourceCopies>
        <copyDir src="$S(PluginDir)/../../Source/TapBootstrap/android/libs/" dst="$S(BuildDir)/libs/" />
    </resourceCopies>

    <buildGradleAdditions>
        <insert>
dependencies.implementation(name: 'TapBootstrap_3.7.0', ext:'aar')
dependencies.implementation('cn.leancloud:realtime-android:8.2.2')
dependencies.implementation('cn.leancloud:storage-android:8.2.2')
dependencies.implementation('io.reactivex.rxjava2:rxandroid:2.1.1')
        </insert>
    </buildGradleAdditions>
</root>